tfserve/__init__.py
tfserve/graph_utils.py
tfserve/handler.py
tfserve/helper.py
tfserve/json_handler.py
tfserve/loader.py
tfserve/main.py
tfserve/tfserve.py
tfserve-0.3.dist-info/METADATA
tfserve-0.3.dist-info/RECORD
tfserve-0.3.dist-info/WHEEL
tfserve-0.3.dist-info/entry_points.txt
tfserve-0.3.dist-info/top_level.txt
