Metadata-Version: 2.1
Name: tfserve
Version: 0.3
Summary: Serve TF models simple and easy as an HTTP API server.
Home-page: http://github.com/iitzco/tfserve
Author: Ivan Itzcovich
Author-email: i.itzcovich@gmail.com
License: MIT
Keywords: tensorflow deep-learning serving
Platform: any
Classifier: License :: OSI Approved :: MIT License
Classifier: Topic :: Internet :: WWW/HTTP :: HTTP Servers
Classifier: Topic :: Internet :: WWW/HTTP :: WSGI
Classifier: Topic :: Internet :: WWW/HTTP :: WSGI :: Application
Classifier: Topic :: Internet :: WWW/HTTP :: WSGI :: Middleware
Classifier: Topic :: Internet :: WWW/HTTP :: WSGI :: Server
Classifier: Topic :: Software Development :: Libraries :: Application Frameworks
Classifier: Programming Language :: Python :: 3.5
Classifier: Programming Language :: Python :: 3.6
Classifier: Programming Language :: Python :: 3.7
Requires-Python: >3.5
Requires-Dist: apistar (==0.5.41)
Requires-Dist: numpy
Requires-Dist: nose
Requires-Dist: Werkzeug
